sequoia/__init__.py
sequoia/auth.py
sequoia/client.py
sequoia/env.py
sequoia/error.py
sequoia/http.py
sequoia/registry.py
sequoia/util.py
sequoia/__pycache__/__init__.cpython-39.pyc
sequoia/criteria/__init__.py
sequoia/criteria/_criteria.py
sequoia_client_sdk-4.4.0.dist-info/LICENSE
sequoia_client_sdk-4.4.0.dist-info/METADATA
sequoia_client_sdk-4.4.0.dist-info/WHEEL
sequoia_client_sdk-4.4.0.dist-info/top_level.txt
sequoia_client_sdk-4.4.0.dist-info/RECORD
