Metadata-Version: 2.1
Name: sequoia-client-sdk
Version: 4.4.0
Summary: Sequoia Python Client SDK
Home-page: https://github.com/pikselpalette/sequoia-python-client-sdk
Author: Piksel
Maintainer: Piksel
License: Apache
Download-URL: https://github.com/pikselpalette/sequoia-python-client-sdk
Keywords: python
Platform: UNKNOWN
Classifier: Development Status :: 5 - Production/Stable
Classifier: Intended Audience :: Developers
Classifier: License :: OSI Approved :: Apache Software License
Classifier: Natural Language :: English
Classifier: Programming Language :: Python
Classifier: Programming Language :: Python :: 3.6
Classifier: Programming Language :: Python :: 3.7
Classifier: Programming Language :: Python :: 3.8
Classifier: Programming Language :: Python :: 3.9
Classifier: Topic :: Software Development :: Libraries :: Python Modules
Requires-Dist: backoff (==1.10.*)
Requires-Dist: chardet (==4.0.*)
Requires-Dist: requests (==2.25.*)
Requires-Dist: requests-oauthlib (==1.3.*)
Requires-Dist: urllib3 (==1.26.*)
